codemail/__init__.py
codemail/codex_client.py
codemail/config.py
codemail/email_utils.py
codemail/log.py
codemail/mailer.py
codemail/markdown_render.py
codemail/prompt.py
codemail/runner.py
codemail/state.py
codemail-0.1.1.dist-info/licenses/LICENSE
codemail-0.1.1.dist-info/METADATA
codemail-0.1.1.dist-info/WHEEL
codemail-0.1.1.dist-info/entry_points.txt
codemail-0.1.1.dist-info/top_level.txt
codemail-0.1.1.dist-info/RECORD
