Metadata-Version: 2.4
Name: codemail
Version: 0.1.1
Summary: Email-ingest automation for Codex tasks
Author: Branch Manager
License: MIT
Project-URL: Homepage, https://github.com/BranchManager69/codemail
Project-URL: Issues, https://github.com/BranchManager69/codemail/issues
Requires-Python: >=3.10
License-File: LICENSE
Requires-Dist: markdown<4,>=3.5
Dynamic: license-file
